[
  {
    "pair": "EUR/USD",
    "price": 1.16904,
    "direction": "DOWN",
    "confidence": 53.9,
    "tp": 1.16789,
    "sl": 1.16982,
    "tp_pips": 11.6,
    "sl_pips": 7.7,
    "kelly_pct": 23.2,
    "atr": 0.00077,
    "rsi": 36.8,
    "zscore": -0.77,
    "macd_bull": false,
    "markov_state": "DDU",
    "markov_p_up": 49.3,
    "markov_obs": 69,
    "ind_score": -0.128,
    "recent_candles": [
      "D",
      "D",
      "D",
      "D",
      "U"
    ],
    "last_candle": "2026-04-10 08:00 UTC",
    "candles_used": 523,
    "error": null
  },
  {
    "pair": "GBP/USD",
    "price": 1.34214,
    "direction": "DOWN",
    "confidence": 56.9,
    "tp": 1.34069,
    "sl": 1.34311,
    "tp_pips": 14.5,
    "sl_pips": 9.7,
    "kelly_pct": 25.0,
    "atr": 0.00097,
    "rsi": 38.2,
    "zscore": -0.65,
    "macd_bull": false,
    "markov_state": "DDU",
    "markov_p_up": 43.3,
    "markov_obs": 67,
    "ind_score": -0.14,
    "recent_candles": [
      "D",
      "D",
      "D",
      "D",
      "U"
    ],
    "last_candle": "2026-04-10 08:00 UTC",
    "candles_used": 523,
    "error": null
  },
  {
    "pair": "USD/JPY",
    "price": 159.27499,
    "direction": "UP",
    "confidence": 54.7,
    "tp": 159.4806,
    "sl": 159.13792,
    "tp_pips": 20.6,
    "sl_pips": 13.7,
    "kelly_pct": 24.5,
    "atr": 0.13707,
    "rsi": 63.3,
    "zscore": 1.19,
    "macd_bull": true,
    "markov_state": "UUD",
    "markov_p_up": 55.2,
    "markov_obs": 67,
    "ind_score": 0.084,
    "recent_candles": [
      "U",
      "U",
      "U",
      "U",
      "D"
    ],
    "last_candle": "2026-04-10 08:00 UTC",
    "candles_used": 522,
    "error": null
  },
  {
    "pair": "USD/CHF",
    "price": 0.78987,
    "direction": "UP",
    "confidence": 59.9,
    "tp": 0.79121,
    "sl": 0.78898,
    "tp_pips": 13.4,
    "sl_pips": 9.0,
    "kelly_pct": 25.0,
    "atr": 0.0009,
    "rsi": 44.6,
    "zscore": -0.26,
    "macd_bull": true,
    "markov_state": "DUD",
    "markov_p_up": 57.6,
    "markov_obs": 59,
    "ind_score": 0.235,
    "recent_candles": [
      "U",
      "D",
      "D",
      "U",
      "D"
    ],
    "last_candle": "2026-04-10 08:00 UTC",
    "candles_used": 521,
    "error": null
  },
  {
    "pair": "AUD/USD",
    "price": 0.70608,
    "direction": "DOWN",
    "confidence": 55.7,
    "tp": 0.70503,
    "sl": 0.70678,
    "tp_pips": 10.5,
    "sl_pips": 7.0,
    "kelly_pct": 25.0,
    "atr": 0.0007,
    "rsi": 32.9,
    "zscore": -1.13,
    "macd_bull": false,
    "markov_state": "DDU",
    "markov_p_up": 42.9,
    "markov_obs": 63,
    "ind_score": -0.091,
    "recent_candles": [
      "D",
      "U",
      "D",
      "D",
      "U"
    ],
    "last_candle": "2026-04-10 08:00 UTC",
    "candles_used": 526,
    "error": null
  },
  {
    "pair": "USD/CAD",
    "price": 1.3837,
    "direction": "DOWN",
    "confidence": 52.1,
    "tp": 1.38205,
    "sl": 1.3848,
    "tp_pips": 16.5,
    "sl_pips": 11.0,
    "kelly_pct": 20.2,
    "atr": 0.0011,
    "rsi": 64.2,
    "zscore": 1.81,
    "macd_bull": true,
    "markov_state": "UUD",
    "markov_p_up": 54.3,
    "markov_obs": 70,
    "ind_score": -0.147,
    "recent_candles": [
      "D",
      "U",
      "U",
      "U",
      "D"
    ],
    "last_candle": "2026-04-10 08:00 UTC",
    "candles_used": 522,
    "error": null
  },
  {
    "pair": "NZD/USD",
    "price": 0.58394,
    "direction": "UP",
    "confidence": 55.0,
    "tp": 0.58497,
    "sl": 0.58325,
    "tp_pips": 10.3,
    "sl_pips": 6.9,
    "kelly_pct": 25.0,
    "atr": 0.00069,
    "rsi": 34.7,
    "zscore": -1.49,
    "macd_bull": false,
    "markov_state": "DDU",
    "markov_p_up": 54.1,
    "markov_obs": 61,
    "ind_score": 0.113,
    "recent_candles": [
      "D",
      "D",
      "D",
      "D",
      "U"
    ],
    "last_candle": "2026-04-10 08:00 UTC",
    "candles_used": 526,
    "error": null
  }
]