[
  {
    "pair": "EUR/USD",
    "price": 1.14312,
    "direction": "DOWN",
    "confidence": 55.7,
    "tp": 1.14119,
    "sl": 1.1444,
    "tp_pips": 19.3,
    "sl_pips": 12.8,
    "kelly_pct": 25.0,
    "atr": 0.00128,
    "rsi": 54.0,
    "zscore": 1.65,
    "macd_bull": true,
    "markov_state": "UUU",
    "markov_p_up": 45.2,
    "markov_obs": 42,
    "ind_score": -0.13,
    "recent_candles": [
      "D",
      "U",
      "U",
      "U",
      "U"
    ],
    "last_candle": "2026-07-08 20:00 UTC",
    "candles_used": 525,
    "error": null
  },
  {
    "pair": "GBP/USD",
    "price": 1.34054,
    "direction": "DOWN",
    "confidence": 53.4,
    "tp": 1.33774,
    "sl": 1.3424,
    "tp_pips": 27.9,
    "sl_pips": 18.6,
    "kelly_pct": 22.3,
    "atr": 0.00186,
    "rsi": 66.6,
    "zscore": 2.1,
    "macd_bull": true,
    "markov_state": "UUU",
    "markov_p_up": 52.6,
    "markov_obs": 57,
    "ind_score": -0.167,
    "recent_candles": [
      "D",
      "U",
      "U",
      "U",
      "U"
    ],
    "last_candle": "2026-07-08 20:00 UTC",
    "candles_used": 525,
    "error": null
  },
  {
    "pair": "USD/JPY",
    "price": 162.45799,
    "direction": "DOWN",
    "confidence": 56.3,
    "tp": 162.2301,
    "sl": 162.60992,
    "tp_pips": 22.8,
    "sl_pips": 15.2,
    "kelly_pct": 25.0,
    "atr": 0.15193,
    "rsi": 59.4,
    "zscore": 0.18,
    "macd_bull": false,
    "markov_state": "DDD",
    "markov_p_up": 50.0,
    "markov_obs": 42,
    "ind_score": -0.228,
    "recent_candles": [
      "U",
      "D",
      "D",
      "D",
      "D"
    ],
    "last_candle": "2026-07-08 20:00 UTC",
    "candles_used": 524,
    "error": null
  },
  {
    "pair": "USD/CHF",
    "price": 0.80741,
    "direction": "DOWN",
    "confidence": 51.3,
    "tp": 0.80546,
    "sl": 0.80871,
    "tp_pips": 19.5,
    "sl_pips": 13.0,
    "kelly_pct": 18.8,
    "atr": 0.0013,
    "rsi": 47.1,
    "zscore": -1.06,
    "macd_bull": false,
    "markov_state": "DDD",
    "markov_p_up": 53.2,
    "markov_obs": 62,
    "ind_score": -0.098,
    "recent_candles": [
      "U",
      "D",
      "D",
      "D",
      "D"
    ],
    "last_candle": "2026-07-08 20:00 UTC",
    "candles_used": 523,
    "error": null
  },
  {
    "pair": "AUD/USD",
    "price": 0.69411,
    "direction": "DOWN",
    "confidence": 55.5,
    "tp": 0.69224,
    "sl": 0.69535,
    "tp_pips": 18.7,
    "sl_pips": 12.4,
    "kelly_pct": 25.0,
    "atr": 0.00124,
    "rsi": 48.3,
    "zscore": 0.89,
    "macd_bull": true,
    "markov_state": "UUU",
    "markov_p_up": 30.8,
    "markov_obs": 39,
    "ind_score": 0.116,
    "recent_candles": [
      "D",
      "U",
      "U",
      "U",
      "U"
    ],
    "last_candle": "2026-07-08 20:00 UTC",
    "candles_used": 525,
    "error": null
  },
  {
    "pair": "USD/CAD",
    "price": 1.4159,
    "direction": "UP",
    "confidence": 53.4,
    "tp": 1.41887,
    "sl": 1.41392,
    "tp_pips": 29.7,
    "sl_pips": 19.8,
    "kelly_pct": 22.3,
    "atr": 0.00198,
    "rsi": 38.7,
    "zscore": -1.48,
    "macd_bull": false,
    "markov_state": "UDD",
    "markov_p_up": 50.8,
    "markov_obs": 65,
    "ind_score": 0.112,
    "recent_candles": [
      "U",
      "D",
      "U",
      "D",
      "D"
    ],
    "last_candle": "2026-07-08 20:00 UTC",
    "candles_used": 526,
    "error": null
  },
  {
    "pair": "NZD/USD",
    "price": 0.57107,
    "direction": "DOWN",
    "confidence": 50.8,
    "tp": 0.56938,
    "sl": 0.57219,
    "tp_pips": 16.9,
    "sl_pips": 11.2,
    "kelly_pct": 18.0,
    "atr": 0.00112,
    "rsi": 46.3,
    "zscore": 0.92,
    "macd_bull": true,
    "markov_state": "UUU",
    "markov_p_up": 41.3,
    "markov_obs": 46,
    "ind_score": 0.113,
    "recent_candles": [
      "D",
      "U",
      "U",
      "U",
      "U"
    ],
    "last_candle": "2026-07-08 20:00 UTC",
    "candles_used": 525,
    "error": null
  }
]