[
  {
    "pair": "EUR/USD",
    "price": 1.15327,
    "direction": "UP",
    "confidence": 52.0,
    "tp": 1.15514,
    "sl": 1.15202,
    "tp_pips": 18.7,
    "sl_pips": 12.5,
    "kelly_pct": 20.0,
    "atr": 0.00125,
    "rsi": 38.0,
    "zscore": -2.25,
    "macd_bull": false,
    "markov_state": "DDD",
    "markov_p_up": 44.2,
    "markov_obs": 104,
    "ind_score": 0.167,
    "recent_candles": [
      "D",
      "D",
      "D",
      "D",
      "D"
    ],
    "last_candle": "2026-06-10 23:00 UTC",
    "candles_used": 525,
    "error": null
  },
  {
    "pair": "GBP/USD",
    "price": 1.33574,
    "direction": "UP",
    "confidence": 55.8,
    "tp": 1.3381,
    "sl": 1.33416,
    "tp_pips": 23.6,
    "sl_pips": 15.8,
    "kelly_pct": 25.0,
    "atr": 0.00158,
    "rsi": 39.6,
    "zscore": -2.39,
    "macd_bull": false,
    "markov_state": "DUD",
    "markov_p_up": 52.7,
    "markov_obs": 74,
    "ind_score": 0.167,
    "recent_candles": [
      "D",
      "D",
      "D",
      "U",
      "D"
    ],
    "last_candle": "2026-06-10 23:00 UTC",
    "candles_used": 525,
    "error": null
  },
  {
    "pair": "USD/JPY",
    "price": 160.51401,
    "direction": "DOWN",
    "confidence": 57.3,
    "tp": 160.37001,
    "sl": 160.61,
    "tp_pips": 14.4,
    "sl_pips": 9.6,
    "kelly_pct": 25.0,
    "atr": 0.096,
    "rsi": 59.6,
    "zscore": 1.11,
    "macd_bull": false,
    "markov_state": "DDU",
    "markov_p_up": 53.4,
    "markov_obs": 58,
    "ind_score": -0.323,
    "recent_candles": [
      "D",
      "U",
      "D",
      "D",
      "U"
    ],
    "last_candle": "2026-06-10 23:00 UTC",
    "candles_used": 522,
    "error": null
  },
  {
    "pair": "USD/CHF",
    "price": 0.79997,
    "direction": "DOWN",
    "confidence": 57.1,
    "tp": 0.79793,
    "sl": 0.80133,
    "tp_pips": 20.4,
    "sl_pips": 13.6,
    "kelly_pct": 25.0,
    "atr": 0.00136,
    "rsi": 56.9,
    "zscore": 1.86,
    "macd_bull": true,
    "markov_state": "DDU",
    "markov_p_up": 43.5,
    "markov_obs": 69,
    "ind_score": -0.153,
    "recent_candles": [
      "U",
      "U",
      "D",
      "D",
      "U"
    ],
    "last_candle": "2026-06-10 23:00 UTC",
    "candles_used": 522,
    "error": null
  },
  {
    "pair": "AUD/USD",
    "price": 0.69955,
    "direction": "UP",
    "confidence": 54.3,
    "tp": 0.70118,
    "sl": 0.69846,
    "tp_pips": 16.3,
    "sl_pips": 10.9,
    "kelly_pct": 23.8,
    "atr": 0.00109,
    "rsi": 39.3,
    "zscore": -1.9,
    "macd_bull": false,
    "markov_state": "DDD",
    "markov_p_up": 50.0,
    "markov_obs": 76,
    "ind_score": 0.157,
    "recent_candles": [
      "D",
      "D",
      "D",
      "D",
      "D"
    ],
    "last_candle": "2026-06-10 23:00 UTC",
    "candles_used": 525,
    "error": null
  },
  {
    "pair": "USD/CAD",
    "price": 1.3946,
    "direction": "DOWN",
    "confidence": 51.8,
    "tp": 1.39217,
    "sl": 1.39622,
    "tp_pips": 24.3,
    "sl_pips": 16.2,
    "kelly_pct": 19.7,
    "atr": 0.00162,
    "rsi": 60.1,
    "zscore": 1.31,
    "macd_bull": true,
    "markov_state": "DDU",
    "markov_p_up": 51.7,
    "markov_obs": 60,
    "ind_score": -0.094,
    "recent_candles": [
      "U",
      "U",
      "D",
      "D",
      "U"
    ],
    "last_candle": "2026-06-10 23:00 UTC",
    "candles_used": 526,
    "error": null
  },
  {
    "pair": "NZD/USD",
    "price": 0.57897,
    "direction": "DOWN",
    "confidence": 50.7,
    "tp": 0.5774,
    "sl": 0.58002,
    "tp_pips": 15.8,
    "sl_pips": 10.5,
    "kelly_pct": 17.8,
    "atr": 0.00105,
    "rsi": 34.8,
    "zscore": -2.34,
    "macd_bull": false,
    "markov_state": "DDD",
    "markov_p_up": 38.3,
    "markov_obs": 94,
    "ind_score": 0.167,
    "recent_candles": [
      "D",
      "D",
      "D",
      "D",
      "D"
    ],
    "last_candle": "2026-06-10 23:00 UTC",
    "candles_used": 525,
    "error": null
  }
]