[
  {
    "pair": "EUR/USD",
    "price": 1.17426,
    "direction": "DOWN",
    "confidence": 60.5,
    "tp": 1.17283,
    "sl": 1.17522,
    "tp_pips": 14.3,
    "sl_pips": 9.5,
    "kelly_pct": 25.0,
    "atr": 0.00095,
    "rsi": 65.4,
    "zscore": 0.74,
    "macd_bull": false,
    "markov_state": "UDU",
    "markov_p_up": 44.2,
    "markov_obs": 52,
    "ind_score": -0.286,
    "recent_candles": [
      "U",
      "D",
      "U",
      "D",
      "U"
    ],
    "last_candle": "2026-04-27 14:00 UTC",
    "candles_used": 490,
    "error": null
  },
  {
    "pair": "GBP/USD",
    "price": 1.3549,
    "direction": "DOWN",
    "confidence": 57.4,
    "tp": 1.35311,
    "sl": 1.3561,
    "tp_pips": 18.0,
    "sl_pips": 12.0,
    "kelly_pct": 25.0,
    "atr": 0.0012,
    "rsi": 64.8,
    "zscore": 0.71,
    "macd_bull": false,
    "markov_state": "DDU",
    "markov_p_up": 50.8,
    "markov_obs": 59,
    "ind_score": -0.282,
    "recent_candles": [
      "U",
      "D",
      "D",
      "D",
      "U"
    ],
    "last_candle": "2026-04-27 14:00 UTC",
    "candles_used": 490,
    "error": null
  },
  {
    "pair": "USD/JPY",
    "price": 159.256,
    "direction": "UP",
    "confidence": 54.2,
    "tp": 159.47575,
    "sl": 159.1095,
    "tp_pips": 22.0,
    "sl_pips": 14.6,
    "kelly_pct": 23.7,
    "atr": 0.1465,
    "rsi": 38.5,
    "zscore": -0.4,
    "macd_bull": true,
    "markov_state": "UUU",
    "markov_p_up": 44.1,
    "markov_obs": 59,
    "ind_score": 0.25,
    "recent_candles": [
      "D",
      "U",
      "U",
      "U",
      "U"
    ],
    "last_candle": "2026-04-27 14:00 UTC",
    "candles_used": 486,
    "error": null
  },
  {
    "pair": "USD/CHF",
    "price": 0.78422,
    "direction": "DOWN",
    "confidence": 52.2,
    "tp": 0.78299,
    "sl": 0.78504,
    "tp_pips": 12.3,
    "sl_pips": 8.2,
    "kelly_pct": 20.3,
    "atr": 0.00082,
    "rsi": 35.5,
    "zscore": -0.95,
    "macd_bull": false,
    "markov_state": "DUD",
    "markov_p_up": 51.7,
    "markov_obs": 58,
    "ind_score": -0.109,
    "recent_candles": [
      "D",
      "U",
      "D",
      "U",
      "D"
    ],
    "last_candle": "2026-04-27 14:00 UTC",
    "candles_used": 487,
    "error": null
  },
  {
    "pair": "AUD/USD",
    "price": 0.71922,
    "direction": "DOWN",
    "confidence": 52.4,
    "tp": 0.71808,
    "sl": 0.71998,
    "tp_pips": 11.4,
    "sl_pips": 7.6,
    "kelly_pct": 20.7,
    "atr": 0.00076,
    "rsi": 76.2,
    "zscore": 1.23,
    "macd_bull": true,
    "markov_state": "UUU",
    "markov_p_up": 55.2,
    "markov_obs": 67,
    "ind_score": -0.173,
    "recent_candles": [
      "U",
      "D",
      "U",
      "U",
      "U"
    ],
    "last_candle": "2026-04-27 14:00 UTC",
    "candles_used": 490,
    "error": null
  },
  {
    "pair": "USD/CAD",
    "price": 1.36069,
    "direction": "UP",
    "confidence": 57.5,
    "tp": 1.36283,
    "sl": 1.35926,
    "tp_pips": 21.4,
    "sl_pips": 14.3,
    "kelly_pct": 25.0,
    "atr": 0.00143,
    "rsi": 14.8,
    "zscore": -1.31,
    "macd_bull": false,
    "markov_state": "DUD",
    "markov_p_up": 48.0,
    "markov_obs": 75,
    "ind_score": 0.306,
    "recent_candles": [
      "D",
      "U",
      "D",
      "U",
      "D"
    ],
    "last_candle": "2026-04-27 14:00 UTC",
    "candles_used": 489,
    "error": null
  },
  {
    "pair": "NZD/USD",
    "price": 0.59172,
    "direction": "DOWN",
    "confidence": 59.6,
    "tp": 0.59065,
    "sl": 0.59243,
    "tp_pips": 10.6,
    "sl_pips": 7.1,
    "kelly_pct": 25.0,
    "atr": 0.00071,
    "rsi": 76.4,
    "zscore": 1.39,
    "macd_bull": true,
    "markov_state": "UDU",
    "markov_p_up": 40.3,
    "markov_obs": 67,
    "ind_score": -0.192,
    "recent_candles": [
      "U",
      "D",
      "U",
      "D",
      "U"
    ],
    "last_candle": "2026-04-27 14:00 UTC",
    "candles_used": 490,
    "error": null
  }
]