[
  {
    "pair": "EUR/USD",
    "price": 1.16945,
    "direction": "DOWN",
    "confidence": 58.0,
    "tp": 1.16828,
    "sl": 1.17024,
    "tp_pips": 11.7,
    "sl_pips": 7.8,
    "kelly_pct": 25.0,
    "atr": 0.00078,
    "rsi": 30.6,
    "zscore": -0.45,
    "macd_bull": false,
    "markov_state": "DDD",
    "markov_p_up": 42.2,
    "markov_obs": 90,
    "ind_score": -0.162,
    "recent_candles": [
      "D",
      "U",
      "D",
      "D",
      "D"
    ],
    "last_candle": "2026-04-10 06:00 UTC",
    "candles_used": 523,
    "error": null
  },
  {
    "pair": "GBP/USD",
    "price": 1.34218,
    "direction": "DOWN",
    "confidence": 56.9,
    "tp": 1.34072,
    "sl": 1.34316,
    "tp_pips": 14.7,
    "sl_pips": 9.8,
    "kelly_pct": 25.0,
    "atr": 0.00098,
    "rsi": 32.2,
    "zscore": -0.75,
    "macd_bull": false,
    "markov_state": "DDU",
    "markov_p_up": 42.6,
    "markov_obs": 68,
    "ind_score": -0.13,
    "recent_candles": [
      "D",
      "D",
      "D",
      "D",
      "U"
    ],
    "last_candle": "2026-04-10 06:00 UTC",
    "candles_used": 523,
    "error": null
  },
  {
    "pair": "USD/JPY",
    "price": 159.229,
    "direction": "DOWN",
    "confidence": 50.2,
    "tp": 159.02404,
    "sl": 159.36565,
    "tp_pips": 20.5,
    "sl_pips": 13.7,
    "kelly_pct": 17.0,
    "atr": 0.13664,
    "rsi": 70.7,
    "zscore": 1.29,
    "macd_bull": true,
    "markov_state": "UUD",
    "markov_p_up": 55.9,
    "markov_obs": 68,
    "ind_score": -0.103,
    "recent_candles": [
      "U",
      "D",
      "U",
      "U",
      "D"
    ],
    "last_candle": "2026-04-10 06:00 UTC",
    "candles_used": 521,
    "error": null
  },
  {
    "pair": "USD/CHF",
    "price": 0.7901,
    "direction": "UP",
    "confidence": 54.8,
    "tp": 0.79146,
    "sl": 0.7892,
    "tp_pips": 13.6,
    "sl_pips": 9.0,
    "kelly_pct": 24.7,
    "atr": 0.0009,
    "rsi": 62.0,
    "zscore": 0.03,
    "macd_bull": true,
    "markov_state": "UDD",
    "markov_p_up": 48.1,
    "markov_obs": 54,
    "ind_score": 0.206,
    "recent_candles": [
      "U",
      "D",
      "U",
      "D",
      "D"
    ],
    "last_candle": "2026-04-10 06:00 UTC",
    "candles_used": 521,
    "error": null
  },
  {
    "pair": "AUD/USD",
    "price": 0.70711,
    "direction": "DOWN",
    "confidence": 54.6,
    "tp": 0.70611,
    "sl": 0.70778,
    "tp_pips": 10.0,
    "sl_pips": 6.7,
    "kelly_pct": 24.3,
    "atr": 0.00067,
    "rsi": 34.0,
    "zscore": -0.08,
    "macd_bull": false,
    "markov_state": "DUD",
    "markov_p_up": 52.0,
    "markov_obs": 75,
    "ind_score": -0.2,
    "recent_candles": [
      "D",
      "U",
      "D",
      "U",
      "D"
    ],
    "last_candle": "2026-04-10 06:00 UTC",
    "candles_used": 526,
    "error": null
  },
  {
    "pair": "USD/CAD",
    "price": 1.38242,
    "direction": "UP",
    "confidence": 56.6,
    "tp": 1.38394,
    "sl": 1.3814,
    "tp_pips": 15.2,
    "sl_pips": 10.2,
    "kelly_pct": 25.0,
    "atr": 0.00102,
    "rsi": 57.3,
    "zscore": 0.51,
    "macd_bull": true,
    "markov_state": "DUD",
    "markov_p_up": 55.2,
    "markov_obs": 67,
    "ind_score": 0.155,
    "recent_candles": [
      "U",
      "D",
      "D",
      "U",
      "D"
    ],
    "last_candle": "2026-04-10 06:00 UTC",
    "candles_used": 523,
    "error": null
  },
  {
    "pair": "NZD/USD",
    "price": 0.585,
    "direction": "DOWN",
    "confidence": 52.9,
    "tp": 0.58401,
    "sl": 0.58566,
    "tp_pips": 9.9,
    "sl_pips": 6.6,
    "kelly_pct": 21.5,
    "atr": 0.00066,
    "rsi": 34.1,
    "zscore": -0.48,
    "macd_bull": false,
    "markov_state": "DDU",
    "markov_p_up": 53.2,
    "markov_obs": 62,
    "ind_score": -0.159,
    "recent_candles": [
      "D",
      "U",
      "D",
      "D",
      "U"
    ],
    "last_candle": "2026-04-10 06:00 UTC",
    "candles_used": 526,
    "error": null
  }
]