[
  {
    "pair": "EUR/USD",
    "price": 1.17343,
    "direction": "DOWN",
    "confidence": 58.1,
    "tp": 1.17239,
    "sl": 1.17413,
    "tp_pips": 10.5,
    "sl_pips": 7.0,
    "kelly_pct": 25.0,
    "atr": 0.0007,
    "rsi": 50.0,
    "zscore": 0.51,
    "macd_bull": false,
    "markov_state": "UDD",
    "markov_p_up": 48.1,
    "markov_obs": 79,
    "ind_score": -0.262,
    "recent_candles": [
      "D",
      "U",
      "U",
      "D",
      "D"
    ],
    "last_candle": "2026-05-01 04:00 UTC",
    "candles_used": 523,
    "error": null
  },
  {
    "pair": "GBP/USD",
    "price": 1.36017,
    "direction": "DOWN",
    "confidence": 59.2,
    "tp": 1.35871,
    "sl": 1.36115,
    "tp_pips": 14.6,
    "sl_pips": 9.7,
    "kelly_pct": 25.0,
    "atr": 0.00097,
    "rsi": 61.9,
    "zscore": 0.63,
    "macd_bull": false,
    "markov_state": "UDD",
    "markov_p_up": 46.3,
    "markov_obs": 67,
    "ind_score": -0.274,
    "recent_candles": [
      "U",
      "U",
      "U",
      "D",
      "D"
    ],
    "last_candle": "2026-05-01 04:00 UTC",
    "candles_used": 523,
    "error": null
  },
  {
    "pair": "USD/JPY",
    "price": 157.125,
    "direction": "UP",
    "confidence": 52.8,
    "tp": 157.47996,
    "sl": 156.88836,
    "tp_pips": 35.5,
    "sl_pips": 23.7,
    "kelly_pct": 21.3,
    "atr": 0.23664,
    "rsi": 68.7,
    "zscore": 0.31,
    "macd_bull": true,
    "markov_state": "UDD",
    "markov_p_up": 45.5,
    "markov_obs": 55,
    "ind_score": 0.176,
    "recent_candles": [
      "U",
      "U",
      "U",
      "D",
      "D"
    ],
    "last_candle": "2026-05-01 04:00 UTC",
    "candles_used": 519,
    "error": null
  },
  {
    "pair": "USD/CHF",
    "price": 0.7816,
    "direction": "UP",
    "confidence": 57.2,
    "tp": 0.78303,
    "sl": 0.78065,
    "tp_pips": 14.3,
    "sl_pips": 9.5,
    "kelly_pct": 25.0,
    "atr": 0.00095,
    "rsi": 43.4,
    "zscore": -0.52,
    "macd_bull": true,
    "markov_state": "DUU",
    "markov_p_up": 50.0,
    "markov_obs": 72,
    "ind_score": 0.262,
    "recent_candles": [
      "D",
      "D",
      "D",
      "U",
      "U"
    ],
    "last_candle": "2026-05-01 04:00 UTC",
    "candles_used": 520,
    "error": null
  },
  {
    "pair": "AUD/USD",
    "price": 0.71963,
    "direction": "DOWN",
    "confidence": 55.3,
    "tp": 0.71865,
    "sl": 0.72029,
    "tp_pips": 9.8,
    "sl_pips": 6.5,
    "kelly_pct": 25.0,
    "atr": 0.00065,
    "rsi": 54.3,
    "zscore": 0.44,
    "macd_bull": false,
    "markov_state": "DDD",
    "markov_p_up": 53.7,
    "markov_obs": 54,
    "ind_score": -0.254,
    "recent_candles": [
      "D",
      "U",
      "D",
      "D",
      "D"
    ],
    "last_candle": "2026-05-01 04:00 UTC",
    "candles_used": 523,
    "error": null
  },
  {
    "pair": "USD/CAD",
    "price": 1.35808,
    "direction": "UP",
    "confidence": 53.9,
    "tp": 1.35994,
    "sl": 1.35684,
    "tp_pips": 18.6,
    "sl_pips": 12.4,
    "kelly_pct": 23.2,
    "atr": 0.00124,
    "rsi": 18.1,
    "zscore": -0.74,
    "macd_bull": false,
    "markov_state": "DUU",
    "markov_p_up": 56.6,
    "markov_obs": 53,
    "ind_score": 0.034,
    "recent_candles": [
      "D",
      "D",
      "D",
      "U",
      "U"
    ],
    "last_candle": "2026-05-01 04:00 UTC",
    "candles_used": 522,
    "error": null
  },
  {
    "pair": "NZD/USD",
    "price": 0.58997,
    "direction": "DOWN",
    "confidence": 57.4,
    "tp": 0.58907,
    "sl": 0.59057,
    "tp_pips": 9.0,
    "sl_pips": 6.0,
    "kelly_pct": 25.0,
    "atr": 0.0006,
    "rsi": 63.7,
    "zscore": 0.33,
    "macd_bull": false,
    "markov_state": "DDD",
    "markov_p_up": 48.4,
    "markov_obs": 64,
    "ind_score": -0.242,
    "recent_candles": [
      "D",
      "U",
      "D",
      "D",
      "D"
    ],
    "last_candle": "2026-05-01 04:00 UTC",
    "candles_used": 523,
    "error": null
  }
]