[
  {
    "pair": "EUR/USD",
    "price": 1.15234,
    "direction": "UP",
    "confidence": 55.0,
    "tp": 1.15394,
    "sl": 1.15128,
    "tp_pips": 16.0,
    "sl_pips": 10.6,
    "kelly_pct": 25.0,
    "atr": 0.00106,
    "rsi": 24.5,
    "zscore": -0.72,
    "macd_bull": true,
    "markov_state": "UDD",
    "markov_p_up": 39.1,
    "markov_obs": 69,
    "ind_score": 0.36,
    "recent_candles": [
      "D",
      "U",
      "U",
      "D",
      "D"
    ],
    "last_candle": "2026-06-08 06:00 UTC",
    "candles_used": 483,
    "error": null
  },
  {
    "pair": "GBP/USD",
    "price": 1.33289,
    "direction": "DOWN",
    "confidence": 51.4,
    "tp": 1.33078,
    "sl": 1.3343,
    "tp_pips": 21.1,
    "sl_pips": 14.1,
    "kelly_pct": 19.0,
    "atr": 0.00141,
    "rsi": 20.6,
    "zscore": -0.83,
    "macd_bull": false,
    "markov_state": "DDD",
    "markov_p_up": 46.4,
    "markov_obs": 69,
    "ind_score": 0.009,
    "recent_candles": [
      "D",
      "U",
      "D",
      "D",
      "D"
    ],
    "last_candle": "2026-06-08 06:00 UTC",
    "candles_used": 483,
    "error": null
  },
  {
    "pair": "USD/JPY",
    "price": 160.27499,
    "direction": "UP",
    "confidence": 61.1,
    "tp": 160.45628,
    "sl": 160.15414,
    "tp_pips": 18.1,
    "sl_pips": 12.1,
    "kelly_pct": 25.0,
    "atr": 0.12086,
    "rsi": 60.2,
    "zscore": 0.45,
    "macd_bull": true,
    "markov_state": "DUD",
    "markov_p_up": 64.7,
    "markov_obs": 68,
    "ind_score": 0.161,
    "recent_candles": [
      "U",
      "U",
      "D",
      "U",
      "D"
    ],
    "last_candle": "2026-06-08 06:00 UTC",
    "candles_used": 480,
    "error": null
  },
  {
    "pair": "USD/CHF",
    "price": 0.79796,
    "direction": "DOWN",
    "confidence": 51.7,
    "tp": 0.79619,
    "sl": 0.79914,
    "tp_pips": 17.7,
    "sl_pips": 11.8,
    "kelly_pct": 19.5,
    "atr": 0.00118,
    "rsi": 76.1,
    "zscore": 1.03,
    "macd_bull": true,
    "markov_state": "DDU",
    "markov_p_up": 45.3,
    "markov_obs": 64,
    "ind_score": 0.016,
    "recent_candles": [
      "U",
      "U",
      "D",
      "D",
      "U"
    ],
    "last_candle": "2026-06-08 06:00 UTC",
    "candles_used": 480,
    "error": null
  },
  {
    "pair": "AUD/USD",
    "price": 0.70398,
    "direction": "UP",
    "confidence": 59.7,
    "tp": 0.70574,
    "sl": 0.7028,
    "tp_pips": 17.6,
    "sl_pips": 11.7,
    "kelly_pct": 25.0,
    "atr": 0.00117,
    "rsi": 25.7,
    "zscore": -0.91,
    "macd_bull": true,
    "markov_state": "DDD",
    "markov_p_up": 49.3,
    "markov_obs": 67,
    "ind_score": 0.363,
    "recent_candles": [
      "D",
      "U",
      "D",
      "D",
      "D"
    ],
    "last_candle": "2026-06-08 06:00 UTC",
    "candles_used": 483,
    "error": null
  },
  {
    "pair": "USD/CAD",
    "price": 1.39472,
    "direction": "UP",
    "confidence": 52.6,
    "tp": 1.39651,
    "sl": 1.39353,
    "tp_pips": 17.9,
    "sl_pips": 11.9,
    "kelly_pct": 21.0,
    "atr": 0.00119,
    "rsi": 64.7,
    "zscore": 0.78,
    "macd_bull": true,
    "markov_state": "DDU",
    "markov_p_up": 48.1,
    "markov_obs": 52,
    "ind_score": 0.127,
    "recent_candles": [
      "U",
      "D",
      "D",
      "D",
      "U"
    ],
    "last_candle": "2026-06-08 06:00 UTC",
    "candles_used": 484,
    "error": null
  },
  {
    "pair": "NZD/USD",
    "price": 0.57995,
    "direction": "UP",
    "confidence": 56.0,
    "tp": 0.58126,
    "sl": 0.57907,
    "tp_pips": 13.1,
    "sl_pips": 8.8,
    "kelly_pct": 25.0,
    "atr": 0.00088,
    "rsi": 28.5,
    "zscore": -0.67,
    "macd_bull": true,
    "markov_state": "UDD",
    "markov_p_up": 45.2,
    "markov_obs": 62,
    "ind_score": 0.298,
    "recent_candles": [
      "D",
      "U",
      "U",
      "D",
      "D"
    ],
    "last_candle": "2026-06-08 06:00 UTC",
    "candles_used": 483,
    "error": null
  }
]