[
  {
    "pair": "EUR/USD",
    "price": 1.15902,
    "direction": "UP",
    "confidence": 50.1,
    "tp": 1.1602,
    "sl": 1.15823,
    "tp_pips": 11.8,
    "sl_pips": 7.9,
    "kelly_pct": 16.8,
    "atr": 0.00079,
    "rsi": 29.0,
    "zscore": -2.2,
    "macd_bull": false,
    "markov_state": "UDD",
    "markov_p_up": 39.2,
    "markov_obs": 79,
    "ind_score": 0.18,
    "recent_candles": [
      "D",
      "D",
      "U",
      "D",
      "D"
    ],
    "last_candle": "2026-05-20 08:00 UTC",
    "candles_used": 519,
    "error": null
  },
  {
    "pair": "GBP/USD",
    "price": 1.33817,
    "direction": "UP",
    "confidence": 54.9,
    "tp": 1.33991,
    "sl": 1.33701,
    "tp_pips": 17.4,
    "sl_pips": 11.6,
    "kelly_pct": 24.8,
    "atr": 0.00116,
    "rsi": 36.2,
    "zscore": -2.05,
    "macd_bull": false,
    "markov_state": "DDD",
    "markov_p_up": 50.7,
    "markov_obs": 75,
    "ind_score": 0.167,
    "recent_candles": [
      "D",
      "U",
      "D",
      "D",
      "D"
    ],
    "last_candle": "2026-05-20 08:00 UTC",
    "candles_used": 519,
    "error": null
  },
  {
    "pair": "USD/JPY",
    "price": 159.06599,
    "direction": "DOWN",
    "confidence": 59.9,
    "tp": 158.88289,
    "sl": 159.18807,
    "tp_pips": 18.3,
    "sl_pips": 12.2,
    "kelly_pct": 25.0,
    "atr": 0.12207,
    "rsi": 51.9,
    "zscore": 0.79,
    "macd_bull": false,
    "markov_state": "DUU",
    "markov_p_up": 45.7,
    "markov_obs": 81,
    "ind_score": -0.291,
    "recent_candles": [
      "U",
      "D",
      "D",
      "U",
      "U"
    ],
    "last_candle": "2026-05-20 08:00 UTC",
    "candles_used": 515,
    "error": null
  },
  {
    "pair": "USD/CHF",
    "price": 0.79044,
    "direction": "DOWN",
    "confidence": 52.6,
    "tp": 0.78925,
    "sl": 0.79124,
    "tp_pips": 11.9,
    "sl_pips": 8.0,
    "kelly_pct": 21.0,
    "atr": 0.0008,
    "rsi": 65.1,
    "zscore": 1.43,
    "macd_bull": true,
    "markov_state": "UUU",
    "markov_p_up": 50.7,
    "markov_obs": 67,
    "ind_score": -0.108,
    "recent_candles": [
      "U",
      "U",
      "U",
      "U",
      "U"
    ],
    "last_candle": "2026-05-20 08:00 UTC",
    "candles_used": 516,
    "error": null
  },
  {
    "pair": "AUD/USD",
    "price": 0.71119,
    "direction": "UP",
    "confidence": 54.0,
    "tp": 0.71232,
    "sl": 0.71043,
    "tp_pips": 11.4,
    "sl_pips": 7.6,
    "kelly_pct": 23.3,
    "atr": 0.00076,
    "rsi": 52.8,
    "zscore": 0.77,
    "macd_bull": true,
    "markov_state": "UUU",
    "markov_p_up": 51.0,
    "markov_obs": 51,
    "ind_score": 0.128,
    "recent_candles": [
      "D",
      "U",
      "U",
      "U",
      "U"
    ],
    "last_candle": "2026-05-20 08:00 UTC",
    "candles_used": 519,
    "error": null
  },
  {
    "pair": "USD/CAD",
    "price": 1.3768,
    "direction": "DOWN",
    "confidence": 54.7,
    "tp": 1.37509,
    "sl": 1.37794,
    "tp_pips": 17.1,
    "sl_pips": 11.4,
    "kelly_pct": 24.5,
    "atr": 0.00114,
    "rsi": 70.8,
    "zscore": 1.44,
    "macd_bull": true,
    "markov_state": "UUD",
    "markov_p_up": 46.9,
    "markov_obs": 64,
    "ind_score": -0.119,
    "recent_candles": [
      "U",
      "D",
      "U",
      "U",
      "D"
    ],
    "last_candle": "2026-05-20 08:00 UTC",
    "candles_used": 519,
    "error": null
  },
  {
    "pair": "NZD/USD",
    "price": 0.5837,
    "direction": "UP",
    "confidence": 54.1,
    "tp": 0.58487,
    "sl": 0.58293,
    "tp_pips": 11.7,
    "sl_pips": 7.8,
    "kelly_pct": 23.5,
    "atr": 0.00078,
    "rsi": 51.0,
    "zscore": 0.55,
    "macd_bull": true,
    "markov_state": "UUU",
    "markov_p_up": 50.0,
    "markov_obs": 56,
    "ind_score": 0.151,
    "recent_candles": [
      "D",
      "U",
      "U",
      "U",
      "U"
    ],
    "last_candle": "2026-05-20 08:00 UTC",
    "candles_used": 519,
    "error": null
  }
]